NiukeDichanXingyeQiuzhiGonglveLonghuPian20212022/README.md
NiukeDichanXingyeQiuzhiGonglveLonghuPian20212022/__init__.py
NiukeDichanXingyeQiuzhiGonglveLonghuPian20212022/__main__.py
NiukeDichanXingyeQiuzhiGonglveLonghuPian20212022/file.epub
NiukeDichanXingyeQiuzhiGonglveLonghuPian20212022/index.html
NiukeDichanXingyeQiuzhiGonglveLonghuPian20212022/css/__init__.py
NiukeDichanXingyeQiuzhiGonglveLonghuPian20212022/css/annotations.css
NiukeDichanXingyeQiuzhiGonglveLonghuPian20212022/css/main.css
NiukeDichanXingyeQiuzhiGonglveLonghuPian20212022/css/normalize.css
NiukeDichanXingyeQiuzhiGonglveLonghuPian20212022/css/popup.css
NiukeDichanXingyeQiuzhiGonglveLonghuPian20212022/font/__init__.py
NiukeDichanXingyeQiuzhiGonglveLonghuPian20212022/font/fontello.eot
NiukeDichanXingyeQiuzhiGonglveLonghuPian20212022/font/fontello.svg
NiukeDichanXingyeQiuzhiGonglveLonghuPian20212022/font/fontello.ttf
NiukeDichanXingyeQiuzhiGonglveLonghuPian20212022/font/fontello.woff
NiukeDichanXingyeQiuzhiGonglveLonghuPian20212022/img/__init__.py
NiukeDichanXingyeQiuzhiGonglveLonghuPian20212022/img/annotator-glyph-sprite.png
NiukeDichanXingyeQiuzhiGonglveLonghuPian20212022/img/annotator-icon-sprite.png
NiukeDichanXingyeQiuzhiGonglveLonghuPian20212022/img/apple-touch-icon.png
NiukeDichanXingyeQiuzhiGonglveLonghuPian20212022/img/cancelfullscreen.png
NiukeDichanXingyeQiuzhiGonglveLonghuPian20212022/img/close.png
NiukeDichanXingyeQiuzhiGonglveLonghuPian20212022/img/fullscreen.png
NiukeDichanXingyeQiuzhiGonglveLonghuPian20212022/img/loader.gif
NiukeDichanXingyeQiuzhiGonglveLonghuPian20212022/img/menu-icon.png
NiukeDichanXingyeQiuzhiGonglveLonghuPian20212022/img/save.png
NiukeDichanXingyeQiuzhiGonglveLonghuPian20212022/img/saved.png
NiukeDichanXingyeQiuzhiGonglveLonghuPian20212022/img/settings-s.png
NiukeDichanXingyeQiuzhiGonglveLonghuPian20212022/img/settings.png
NiukeDichanXingyeQiuzhiGonglveLonghuPian20212022/img/star.png
NiukeDichanXingyeQiuzhiGonglveLonghuPian20212022/js/__init__.py
niuke_dichan_xingye_qiuzhi_gonglve_longhu_pian_2021_2022-2024.3.6.0.dist-info/METADATA
niuke_dichan_xingye_qiuzhi_gonglve_longhu_pian_2021_2022-2024.3.6.0.dist-info/WHEEL
niuke_dichan_xingye_qiuzhi_gonglve_longhu_pian_2021_2022-2024.3.6.0.dist-info/entry_points.txt
niuke_dichan_xingye_qiuzhi_gonglve_longhu_pian_2021_2022-2024.3.6.0.dist-info/top_level.txt
niuke_dichan_xingye_qiuzhi_gonglve_longhu_pian_2021_2022-2024.3.6.0.dist-info/RECORD
